processing/__init__.py
processing/combination.py
processing/transformation.py
utils/__init__.py
utils/io.py
utils/plot.py
DescomplicandoACria_oDePacotes_Unimed_marcosmvsfut-0.0.3.dist-info/METADATA
DescomplicandoACria_oDePacotes_Unimed_marcosmvsfut-0.0.3.dist-info/WHEEL
DescomplicandoACria_oDePacotes_Unimed_marcosmvsfut-0.0.3.dist-info/top_level.txt
DescomplicandoACria_oDePacotes_Unimed_marcosmvsfut-0.0.3.dist-info/RECORD
